evgen_task_3-0.0.1.dist-info/licenses/LICENSE
src/__init__.py
src/main_app.py
evgen_task_3-0.0.1.dist-info/METADATA
evgen_task_3-0.0.1.dist-info/WHEEL
evgen_task_3-0.0.1.dist-info/top_level.txt
evgen_task_3-0.0.1.dist-info/RECORD
