Metadata-Version: 2.4
Name: evgen_Task_3
Version: 0.0.1
Summary: task3 python package
Author-email: Evgen <author@gmail.com>
Classifier: Programming Language :: Python :: 3
Classifier: Operating System :: OS Independent
Requires-Python: >=3.9
License-File: LICENSE
Requires-Dist: pytest
Requires-Dist: pytest-mock
Dynamic: license-file
